{
  "generated_at": "2026-04-30 09:53 UTC",
  "ist_time": "2026-04-30 15:22 IST",
  "hour_label": "15:00 \u2014 15:59 IST",
  "market_open": true,
  "spot": {
    "price": 24000.95,
    "day_open": 23996.95,
    "day_high": 24087.45,
    "day_low": 23796.85,
    "cum_return": 0.02,
    "vwap": 23934.48
  },
  "signal": {
    "direction": "FLAT",
    "confidence": "NEUTRAL",
    "prob_up": 50.0,
    "prob_down": 50.0,
    "pred_high": 24075.95,
    "pred_low": 23925.95,
    "orb_status": 0,
    "score": 0
  },
  "options": {
    "pcr_oi": 1.0,
    "max_pain": 24000.95,
    "call_wall": 24200.95,
    "put_wall": 23800.95,
    "atm_iv": 14.0,
    "iv_skew": 0.0,
    "straddle": 200.0,
    "sentiment": "NEUTRAL",
    "total_ce_oi": 0,
    "total_pe_oi": 0
  },
  "gex": {
    "total_gex": 0.0,
    "zero_gamma": 24001.0,
    "regime": "UNKNOWN",
    "strength": 0.0,
    "is_positive": false
  },
  "skew": {
    "skew_25d": 0.0,
    "pc_iv_ratio": 1.0,
    "iv_slope": 0.0,
    "bias": "NEUTRAL"
  },
  "news": {
    "count": 100,
    "sentiment": "MIXED"
  },
  "analysis": {
    "full": "Analysis failed: 429 RESOURCE_EXHAUSTED. {'error': {'code': 429, 'message': 'You exceeded your current quota, please ",
    "summary": "",
    "bull_points": [],
    "bear_points": []
  }
}